main.v
/////////////////////////////////////////////////////////////////////////////////////////
// Filename: voting_machine.v
// Date created: 08-11-2020
// Simulation: iverilog v11, GTKWave 
// Description: Design of a 3 candidate voting machine using state machine.
// Nomencleture: i = Input, o = Output, r = register
//             
/////////////////////////////////////////////////////////////////////////////////////////

module voting_machine #(
parameter idle =  2'b00,					// states and their corresponding numbers
parameter vote =  2'b01,
parameter hold =  2'b10,
parameter finish = 2'b11
)(
    input clk,							
    input rst,							// input High to reset counting  (active high)
    input i_candidate_1,				// input to vote for candidate 1
    input i_candidate_2,				// input to vote for candidate 2
    input i_candidate_3,				// input to vote for candidate 3
    input i_voting_over,				// input high to get total votes after voting is over

    output reg [31:0] o_count1,			// output for total number of votes of candidate 1
    output reg [31:0] o_count2,			// output for total number of votes of candidate 2
    output reg [31:0] o_count3			// output for total number of votes of candidate 3

);	  

reg [31:0] r_cand1_prev;					// store previous value of input for candidate 1
reg [31:0] r_cand2_prev;					// store previous value of input for candidate 2
reg [31:0] r_cand3_prev;					// store previous value of input for candidate 3

reg [31:0] r_counter_1;						// counting register for candidate 1
reg [31:0] r_counter_2;						// counting register for candidate 2
reg [31:0] r_counter_3;						// counting register for candidate 3

reg [1:0] r_present_state, r_next_state;		// present state and next state registers
//reg [1:0] r_state_no;					     // store state number
reg [3:0] r_hold_count;                        //counter for hold state

//////////// always block that assigns next state & internal reg operations /////////////////////////////////// 
always @(posedge clk or negedge rst)
	begin
		case (r_present_state)														

			idle: if (!rst)												// idle state operations
						begin
							r_next_state <= vote;									// assign next state vote when reset low
							//r_state_no <= 2'b01;
						end	

					else
						begin
						//r_present_state = idle;									// present state at the beginning
							r_counter_1 <= 32'b0;										// clear counting registers
							r_counter_2 <= 32'b0;
							r_counter_3 <= 32'b0;
							r_hold_count <= 4'b0000;

							r_next_state <= idle;									// assign next state as idle till reset not low
							//r_state_no <= 2'b0;
						end
				

			vote: if (i_voting_over == 1'b1)									// check if voting is over
						begin
							r_next_state <= finish;								// if over is high go to finish state
							//r_state_no <= 2'b11;
						end
												// if over is low contiue counting
					else if (i_candidate_1 == 1'b0 && r_cand1_prev == 1'b1)         // check falling edge of input candidate1 so only single input is regeistered 
						begin
							r_counter_1 <= r_counter_1 + 1'b1;								// increment counter for candidate 1
							//r_counter_2 <= r_counter_2;									// keep previous value of counter 
							//r_counter_3 <= r_counter_3;									// keep previous value of counter

							r_next_state <= hold;									// got to hold state
							//r_state_no <= 2'b10;
						end

					else if (i_candidate_2 == 1'b0 && r_cand2_prev == 1'b1) 		// check falling edge of input candidate2 so only single input is regeistered
						begin
							//r_counter_1 <= r_counter_1;									// keep previous value of counter 
							r_counter_2 <= r_counter_2 + 1'b1;								// increment counter for candidate 2
							//r_counter_3 <= r_counter_3;									// keep previous value of counter 

							r_next_state <= hold;									// got to hold state
							//r_state_no <= 2'b10;
						end

					else if (i_candidate_3 == 1'b0 && r_cand3_prev == 1'b1) 		// check falling edge of input candidate3 so only single input is regeistered
						begin
							//r_counter_1 <= r_counter_1;									// keep previous value of counter
							//r_counter_2 <= r_counter_2;									// keep previous value of counter
							r_counter_3 <= r_counter_3 + 1'b1;								// increment counter for candidate 3

							r_next_state <= hold;									// got to hold state
							//r_state_no <= 2'b10;
						end
					else															// none of the input present or more than 1 input present at same time
						begin
							r_counter_1 <= r_counter_1;									// keep previous value of counter
							r_counter_2 <= r_counter_2;									
							r_counter_3 <= r_counter_3;

							r_next_state <= vote;
							//r_state_no <= 2'b01;
						end

			hold: if (i_voting_over == 1'b1)									// check if over input is high
						begin
							r_next_state <= finish;									// go to finish state
							//r_state_no <= 2'b11;
						end

					else 
						begin
							if (r_hold_count != 4'b1111) begin
								r_hold_count = r_hold_count + 1'b1;
							end
							else begin
							    r_next_state <= vote;									// if over is low go to vote state
							end
							//r_state_no <= 2'b01;
						end

			finish: if (i_voting_over == 1'b0)										
						begin
							r_next_state <= idle;									// if over is low go to idle state
							//r_state_no <= 2'b0;
						end

					else
						begin
							r_next_state <= finish;									// remain in finish state if over is high
							//r_state_no <= 2'b11;
						end

			default: 
				begin 
					r_counter_1 <= 32'b0;											// default values for resgisters
					r_counter_2 <= 32'b0;
					r_counter_3 <= 32'b0;
					r_hold_count <= 4'b0000;

					r_next_state <= idle;										// by default go to idle state at the begining
					//r_state_no <= 2'b0;
				end
		endcase
	end	  

////////////// always block that performs assignment of regsiters and output on clock signal //////////////////////////////
always @(posedge clk or negedge rst)													// work on positive edge of clock 
	begin				

      if (rst == 1'b1)
			begin
				 r_present_state <= idle;											// remain in idle state when reset is high
													
				 o_count1 <= 32'b0; 												// reset final output count  
				 o_count2 <= 32'b0;
				 o_count3 <= 32'b0;
				 r_hold_count <= 4'b0000;
			end 
			
		else if (rst == 1'b0 && i_voting_over == 1'b1)											// if voting process is i.e.over is high
			begin
				 o_count1 <= r_counter_1; 											// provide value of counting registers at output
				 o_count2 <= r_counter_2;
				 o_count3 <= r_counter_3;
			end
		
		else
			begin
				r_present_state <= r_next_state;									// if reset is low keep assigning next state to present state
				r_cand1_prev <= i_candidate_1;									// keep assigning input of candidate 1 to internal register
				r_cand2_prev <= i_candidate_2;
				r_cand3_prev <= i_candidate_3;
			end
	
	end	

endmodule

tb.v
/////////////////////////////////////////////////////////////////////////////////////////
// Filename: tb_voting_machine.v
// Author: pratik_bhuran 
// Date created: 30-11-2020
// Compiler: iverilog v11 
// Description: Design of testbench for Voting machine with 3 candidate choices .
//version: 2 = added more stimulus and comments
//
/////////////////////////////////////////////////////////////////////////////////////////


`include "main.v"              // `include => *only applicable for iverilog simulation, remove this line while using other simulators
`timescale 1ns/1ns                             // 1 time unit = 1 ns

module tb_voting_machine ();
reg t_clk;
reg t_rst;
reg t_candidate_1;
reg t_candidate_2;
reg t_candidate_3;
reg t_vote_over;

wire [5:0] t_result_1;
wire [5:0] t_result_2;
wire [5:0] t_result_3;

//instansiate component unit under test
voting_machine uut ( 
.clk(t_clk), 
.rst(t_rst), 
.i_candidate_1(t_candidate_1), 
.i_candidate_2(t_candidate_2), 
.i_candidate_3(t_candidate_3), 
.i_voting_over(t_vote_over),
.o_count1(t_result_1),
.o_count2(t_result_2),
.o_count3(t_result_3)
);

//initial value of clock at 0 time
initial t_clk = 1'b1;

// clock generation
always
begin
    #5 t_clk = ~ t_clk;     
end

//stimulus to design
initial
begin
    $monitor ("time = %d, rst = %b, candidate_1 = %b, candidate_2 = %b, candidate_3 = %b, vote_over = %b, result_1 = %3d, result_2 = %3d, result_3 = %3d,\n",
    $time, t_rst, t_candidate_1, t_candidate_2, t_candidate_3, t_vote_over, t_result_1, t_result_2, t_result_3,);

    
    t_rst = 1'b1;
    t_candidate_1 = 1'b0;
    t_candidate_2 = 1'b0;
    t_candidate_3 = 1'b0;
    t_vote_over = 1'b0;

    #20 t_rst = 1'b0;
    #10 t_candidate_1 = 1'b1;              //when button for candidate 1 is pressed
    #10 t_candidate_1 = 1'b0;              //button  for candidate 1 is released

    #20 t_candidate_2 = 1'b1;              //when button for candidate 2 is pressed
    #10 t_candidate_2 = 1'b0;              //button  for candidate 2 is released

    #20 t_candidate_1 = 1'b1;              //when button for candidate 1 is pressed
    #10 t_candidate_1 = 1'b0;              //button  for candidate 1 is released

    #20 t_candidate_3 = 1'b1;               //when button for candidate 3 is pressed
    #10 t_candidate_3 = 1'b0;               //button  for candidate 3 is released
  
    #20 t_candidate_2 = 1'b1;
    #10 t_candidate_2 = 1'b0;

    #20 t_candidate_2 = 1'b1;
    #10 t_candidate_2 = 1'b0;
    
    #20 t_candidate_1 = 1'b1;
    #10 t_candidate_1 = 1'b0;
    
    #20 t_candidate_3 = 1'b1;               //when button for candidate 3 is pressed
    #10 t_candidate_3 = 1'b0;               //button  for candidate 3 is released


    #30 t_vote_over = 1'b1;

    #50 t_rst = 1'b1;                                    //reset when the voting process is over 
    
    //use $finish for simulators other than modelsim
    #60 $stop;                                          // use $stop instead of $finish to keep modelsim simulator open 
end

//.vcd file for gtk wave plot
initial
begin
    $dumpfile ("voting_dumpfile.vcd");
    $dumpvars (0, tb_voting_machine);
end


endmodule

voting_dumpfile.vcd
$date
	Fri Aug 01 22:51:52 2025
$end
$version
	Icarus Verilog
$end
$timescale
	1ns
$end
$scope module tb_voting_machine $end
$var wire 6 ! t_result_3 [5:0] $end
$var wire 6 " t_result_2 [5:0] $end
$var wire 6 # t_result_1 [5:0] $end
$var reg 1 $ t_candidate_1 $end
$var reg 1 % t_candidate_2 $end
$var reg 1 & t_candidate_3 $end
$var reg 1 ' t_clk $end
$var reg 1 ( t_rst $end
$var reg 1 ) t_vote_over $end
$scope module uut $end
$var wire 1 ' clk $end
$var wire 1 $ i_candidate_1 $end
$var wire 1 % i_candidate_2 $end
$var wire 1 & i_candidate_3 $end
$var wire 1 ) i_voting_over $end
$var wire 1 ( rst $end
$var parameter 2 * finish $end
$var parameter 2 + hold $end
$var parameter 2 , idle $end
$var parameter 2 - vote $end
$var reg 32 . o_count1 [31:0] $end
$var reg 32 / o_count2 [31:0] $end
$var reg 32 0 o_count3 [31:0] $end
$var reg 32 1 r_cand1_prev [31:0] $end
$var reg 32 2 r_cand2_prev [31:0] $end
$var reg 32 3 r_cand3_prev [31:0] $end
$var reg 32 4 r_counter_1 [31:0] $end
$var reg 32 5 r_counter_2 [31:0] $end
$var reg 32 6 r_counter_3 [31:0] $end
$var reg 4 7 r_hold_count [3:0] $end
$var reg 2 8 r_next_state [1:0] $end
$var reg 2 9 r_present_state [1:0] $end
$upscope $end
$upscope $end
$enddefinitions $end
$comment Show the parameter values. $end
$dumpall
b1 -
b0 ,
b10 +
b11 *
$end
#0
$dumpvars
b0 9
b0 8
b0 7
b0 6
b0 5
b0 4
bx 3
bx 2
bx 1
b0 0
b0 /
b0 .
0)
1(
1'
0&
0%
0$
b0 #
b0 "
b0 !
$end
#5
0'
#10
1'
#15
0'
#20
b1 8
b0 3
b0 2
b0 1
1'
0(
#25
0'
#30
b1 1
b1 9
1'
1$
#35
0'
#40
b10 8
b1 4
b0 1
1'
0$
#45
0'
#50
b10 9
b1 8
1'
#55
0'
#60
b1 2
b1 9
b1 7
1'
1%
#65
0'
#70
b0 2
b10 8
b1 5
1'
0%
#75
0'
#80
b1 8
b10 9
1'
#85
0'
#90
b1 1
b1 9
b10 7
1'
1$
#95
0'
#100
b10 8
b10 4
b0 1
1'
0$
#105
0'
#110
b10 9
b1 8
1'
#115
0'
#120
b1 3
b1 9
b11 7
1'
1&
#125
0'
#130
b0 3
b10 8
b1 6
1'
0&
#135
0'
#140
b1 8
b10 9
1'
#145
0'
#150
b1 2
b1 9
b100 7
1'
1%
#155
0'
#160
b10 8
b10 5
b0 2
1'
0%
#165
0'
#170
b10 9
b1 8
1'
#175
0'
#180
b1 2
b1 9
b101 7
1'
1%
#185
0'
#190
b0 2
b10 8
b11 5
1'
0%
#195
0'
#200
b1 8
b10 9
1'
#205
0'
#210
b1 1
b1 9
b110 7
1'
1$
#215
0'
#220
b10 8
b11 4
b0 1
1'
0$
#225
0'
#230
b10 9
b1 8
1'
#235
0'
#240
b1 3
b1 9
b111 7
1'
1&
#245
0'
#250
b0 3
b10 8
b10 6
1'
0&
#255
0'
#260
b1 8
b10 9
1'
#265
0'
#270
b1 9
b1000 7
1'
#275
0'
#280
b10 !
b11 "
b11 #
b11 8
b10 0
b11 /
b11 .
1'
1)
#285
0'
#290
1'
#295
0'
#300
1'
#305
0'
#310
1'
#315
0'
#320
1'
#325
0'
#330
b0 !
b0 "
b0 #
b0 7
b0 0
b0 /
b0 .
b0 9
1'
1(
#335
0'
#340
b0 8
b0 6
b0 5
b0 4
1'
